streamduo/__init__.py
streamduo/client.py
streamduo/api/__init__.py
streamduo/api/actor.py
streamduo/api/batch.py
streamduo/api/health.py
streamduo/api/key.py
streamduo/api/record.py
streamduo/api/schema.py
streamduo/api/stream.py
streamduo/models/__init__.py
streamduo/models/batch_data.py
streamduo/models/batch_init_request.py
streamduo/models/key_pair.py
streamduo/models/read_record_request.py
streamduo/models/record.py
streamduo/models/record_request.py
streamduo/models/schema.py
streamduo/validators/__init__.py
streamduo/validators/avro_schema.py
streamduo/validators/frictionless_schema.py
streamduo/validators/great_expectations_schema.py
streamduo/validators/json_schema.py
tests/__init__.py
tests/integration/__init__.py
tests/integration/test_actor.py
tests/integration/test_batch.py
tests/integration/test_health.py
tests/integration/test_keys.py
tests/integration/test_record.py
tests/integration/test_schema.py
tests/integration/test_stream.py
tests/unit/__init__.py
tests/unit/test_actor.py
tests/unit/test_avro_schema.py
tests/unit/test_batch_controller.py
tests/unit/test_friction_schema.py
tests/unit/test_ge_schema.py
tests/unit/test_health.py
tests/unit/test_json_schema.py
tests/unit/test_key.py
tests/unit/test_record.py
streamduo-0.0.35.dist-info/LICENSE.md
streamduo-0.0.35.dist-info/METADATA
streamduo-0.0.35.dist-info/WHEEL
streamduo-0.0.35.dist-info/top_level.txt
streamduo-0.0.35.dist-info/RECORD
